dac/__init__.py
dac/core/__init__.py
dac/core/actions.py
dac/core/data.py
dac/core/path.py
dac/core/scenario.py
dac/core/snippet.py
dac/core/thread.py
dac/gui/__init__.py
dac/gui/base.py
dac/gui/main.py
dac/gui/mcn.py
dac/gui/resources/dac-logo.png
dac/modules/__init__.py
dac/modules/drivetrain/__init__.py
dac/modules/drivetrain/actions.py
dac/modules/nvh/__init__.py
dac/modules/nvh/actions.py
dac/modules/nvh/calc_lib.py
dac/modules/nvh/data.py
dac/modules/timedata/__init__.py
dac/modules/timedata/actions.py
dac/modules/timedata/construct.py
dac/modules/timedata/data_loader.py
dac/modules/timedata/tasks.py
dac/scenarios/0.base.yaml
dac/scenarios/9.test.yaml
miz_dac-0.4.1.dist-info/METADATA
miz_dac-0.4.1.dist-info/WHEEL
miz_dac-0.4.1.dist-info/entry_points.txt
miz_dac-0.4.1.dist-info/top_level.txt
miz_dac-0.4.1.dist-info/RECORD
