Metadata-Version: 2.4
Name: miz-dac
Version: 0.4.1
Summary: Minimal measurement data analysis frame with nodes and container.
Author-email: MIZiper <miziper@163.com>
License: Apache-2.0
Project-URL: Homepage, http://mizip.net/
Project-URL: Repository, https://github.com/MIZiper/dac.git
Keywords: data,context,analysis
Requires-Python: >=3.10
Requires-Dist: click
Requires-Dist: numpy
Requires-Dist: scipy
Requires-Dist: matplotlib
Requires-Dist: pyyaml
Requires-Dist: nptdms
Provides-Extra: gui
Requires-Dist: pyqt5; extra == "gui"
Requires-Dist: qscintilla; extra == "gui"
Provides-Extra: ipy
Requires-Dist: pyqt5; extra == "ipy"
Requires-Dist: qscintilla; extra == "ipy"
Requires-Dist: qtconsole; extra == "ipy"
